nanows/__init__.py
nanows/api.py
nanows/application/__init__.py
nanows/application/nano_websocket_service.py
nanows/domain/__init__.py
nanows/domain/exceptions/__init__.py
nanows/domain/exceptions/websocket_exceptions.py
nanows/domain/interfaces/__init__.py
nanows/domain/interfaces/websocket_client.py
nanows/domain/models/__init__.py
nanows/domain/models/message.py
nanows/domain/models/subscription.py
nanows/infrastructure/__init__.py
nanows/infrastructure/serialization/__init__.py
nanows/infrastructure/serialization/message_factory.py
nanows/infrastructure/websocket/__init__.py
nanows/infrastructure/websocket/websocket_client.py
nanows-2.0.2.dist-info/METADATA
nanows-2.0.2.dist-info/WHEEL
nanows-2.0.2.dist-info/top_level.txt
nanows-2.0.2.dist-info/RECORD
