Metadata-Version: 2.2
Name: nanows
Version: 2.0.2
Summary: A robust, type-safe Python client for interacting with Nano cryptocurrency nodes via WebSockets
Home-page: https://github.com/gr0vity-dev/nanows-v2
Author: gr0vity-dev
Author-email: iq.cc@pm.me
Classifier: Programming Language :: Python :: 3
Classifier: Programming Language :: Python :: 3.8
Classifier: Programming Language :: Python :: 3.9
Classifier: Programming Language :: Python :: 3.10
Classifier: License :: OSI Approved :: MIT License
Classifier: Operating System :: OS Independent
Classifier: Development Status :: 4 - Beta
Classifier: Intended Audience :: Developers
Classifier: Topic :: Software Development :: Libraries :: Python Modules
Requires-Python: >=3.9
Requires-Dist: websockets<16.0,>=15.0
Dynamic: author
Dynamic: author-email
Dynamic: classifier
Dynamic: description
Dynamic: description-content-type
Dynamic: home-page
Dynamic: requires-dist
Dynamic: requires-python
Dynamic: summary
